handle_accept_cookie/__init__.py
handle_accept_cookie/cookie_acceptance_handler.py
tests/__init__.py
tests/test.py
CookieXplorer-0.1.0.dist-info/LICENSE.txt
CookieXplorer-0.1.0.dist-info/METADATA
CookieXplorer-0.1.0.dist-info/WHEEL
CookieXplorer-0.1.0.dist-info/top_level.txt
CookieXplorer-0.1.0.dist-info/RECORD
